pokesel/__Init__.py
pokesel/pokemon.csv
pokesel/random_pokemon.py
pokesel-1.0.2.dist-info/METADATA
pokesel-1.0.2.dist-info/WHEEL
pokesel-1.0.2.dist-info/top_level.txt
pokesel-1.0.2.dist-info/RECORD
